{
  "scriptName": "daiso-mcp",
  "metric": "workersInvocationsAdaptive.requests + httpRequestsAdaptiveGroups.count",
  "aggregation": "script-level plus redirected root GET",
  "includedTraffic": "Worker invocations for daiso-mcp plus redirected GET / traffic on mcp.aka.page where zone analytics retention permits.",
  "rootRedirect": {
    "zoneId": "c987d32286724a5a1fd5586cec7756c1",
    "host": "mcp.aka.page",
    "path": "/",
    "start": "2026-05-27T07:24:50.000Z",
    "rootRequestsRetentionDays": 7
  },
  "timezone": "Asia/Seoul",
  "days": 30,
  "startDate": "2026-06-18",
  "endDate": "2026-07-17",
  "updatedAt": "2026-07-17T15:49:17.292Z",
  "renderedAt": "2026-07-17T15:49:17.292Z",
  "total": 14077291,
  "average": 469243,
  "median": 38218,
  "peak": {
    "date": "2026-07-16",
    "requests": 2140839
  },
  "recent7Total": 12974744,
  "recent7Average": 1853535,
  "previous7Total": 530935,
  "weekOverWeekDiff": 12443809,
  "weekOverWeekPercent": 2343.75375516777,
  "latest": {
    "date": "2026-07-17",
    "requests": 1707162
  },
  "previous": {
    "date": "2026-07-16",
    "requests": 2140839
  },
  "dayOverDayDiff": -433677,
  "dayOverDayPercent": -20.257338361268644,
  "points": [
    {
      "date": "2026-06-18",
      "requests": 36671
    },
    {
      "date": "2026-06-19",
      "requests": 33806
    },
    {
      "date": "2026-06-20",
      "requests": 42489
    },
    {
      "date": "2026-06-21",
      "requests": 27198
    },
    {
      "date": "2026-06-22",
      "requests": 32314
    },
    {
      "date": "2026-06-23",
      "requests": 41400
    },
    {
      "date": "2026-06-24",
      "requests": 46920
    },
    {
      "date": "2026-06-25",
      "requests": 39286
    },
    {
      "date": "2026-06-26",
      "requests": 69751
    },
    {
      "date": "2026-06-27",
      "requests": 23695
    },
    {
      "date": "2026-06-28",
      "requests": 20255
    },
    {
      "date": "2026-06-29",
      "requests": 30686
    },
    {
      "date": "2026-06-30",
      "requests": 31069
    },
    {
      "date": "2026-07-01",
      "requests": 37149
    },
    {
      "date": "2026-07-02",
      "requests": 32248
    },
    {
      "date": "2026-07-03",
      "requests": 26675
    },
    {
      "date": "2026-07-04",
      "requests": 19379
    },
    {
      "date": "2026-07-05",
      "requests": 20179
    },
    {
      "date": "2026-07-06",
      "requests": 33170
    },
    {
      "date": "2026-07-07",
      "requests": 102868
    },
    {
      "date": "2026-07-08",
      "requests": 189386
    },
    {
      "date": "2026-07-09",
      "requests": 132539
    },
    {
      "date": "2026-07-10",
      "requests": 33414
    },
    {
      "date": "2026-07-11",
      "requests": 1816252
    },
    {
      "date": "2026-07-12",
      "requests": 1681032
    },
    {
      "date": "2026-07-13",
      "requests": 1941919
    },
    {
      "date": "2026-07-14",
      "requests": 1779466
    },
    {
      "date": "2026-07-15",
      "requests": 1908074
    },
    {
      "date": "2026-07-16",
      "requests": 2140839
    },
    {
      "date": "2026-07-17",
      "requests": 1707162
    }
  ]
}
